{
  "smartling" : {
    "translate_paths" : ["*/translation"],
    "variants_enabled" : true,
    "translate_mode" : "custom",
    "placeholder_format_custom" : ["%%[^%]+?%%", "%[^%]+?%", "##[^#]+?##", "__[^_]+?__", "[$]\\{[^\\}\\{]+?\\}", "\\{\\{[^\\}\\{]+?\\}\\}", "(?<!\\{)\\{[^\\}\\{]+?\\}(?!\\})"],
    "source_key_paths" : ["/{*}"]
  },
  "song.title.farmerInTheDell" : {
    "translation" : "谷間の農夫"
  },
  "song.title.muffinMan" : {
    "translation" : "マフィン売り"
  },
  "song.title.mulberryBush" : {
    "translation" : "クワの茂み"
  },
  "song.title.dannyBoy" : {
    "translation" : "ダニーボーイ"
  },
  "song.title.vivaldiSpring" : {
    "translation" : "ヴィヴァルディ春"
  },
  "song.title.waterMusic" : {
    "translation" : "水上の音楽"
  },
  "song.title.abaDaba" : {
    "translation" : "Aba Daba Honeymoon"
  },
  "song.title.tisketTasket" : {
    "translation" : "A-Tisket, A-Tasket"
  },
  "song.title.bingo" : {
    "translation" : "ビンゴ"
  },
  "song.title.buffaloGals" : {
    "translation" : "バッファローギャル"
  },
  "song.title.yellowRose" : {
    "translation" : "Yellow Rose"
  },
  "song.title.canCan1" : {
    "translation" : "フレンチカンカン"
  },
  "song.title.canCan2" : {
    "translation" : "フレンチカンカン"
  },
  "song.title.silveryMoon" : {
    "translation" : "By the Light of the Silvery Moon"
  },
  "song.title.laPaloma" : {
    "translation" : "ラ・パロマ"
  },
  "song.title.toccata" : {
    "translation" : "トッカータとフーガ"
  },
  "song.title.wildAboutHarry" : {
    "translation" : "I'm Just Wild About Harry"
  },
  "song.title.camptown" : {
    "translation" : "「草競馬」"
  },
  "song.title.itsyBitsySpider" : {
    "translation" : "「ちっちゃなクモさん」"
  },
  "song.title.beethoven" : {
    "translation" : "「ベートーベンの交響曲第5番」"
  },
  "song.title.popGoesTheWeasel" : {
    "translation" : "「いいやつみつけた」"
  },
  "song.title.rowYourBoat" : {
    "translation" : "「こげこげボート」"
  },
  "song.title.pachebelCanon" : {
    "translation" : "「パッヘルベルのカノン」"
  },
  "song.title.odeToJoy" : {
    "translation" : "「ベートーベンの第九交響曲」"
  },
  "song.title.twinkleTwinkle" : {
    "translation" : "「きらきら星」"
  },
  "song.title.frereJaqcues" : {
    "translation" : "「フレールジャック」"
  },
  "song.title.maryHadALittleLamb" : {
    "translation" : "「メリーさんのひつじ」"
  },
  "song.title.takeMeOutToTheBallgame" : {
    "translation" : "「私を野球に連れてって」"
  },
  "song.title.williamTell" : {
    "translation" : "ウィリアム・テル序曲"
  },
  "song.title.yankeeDoodle" : {
    "translation" : "アルプス一万尺"
  },
  "song.title.beautifulDreamer" : {
    "translation" : "夢路より"
  },
  "song.title.mountainKing" : {
    "translation" : "山の魔王の宮殿にて"
  },
  "song.title.taRaRaBoom" : {
    "translation" : "タララタンタカターン"
  },
  "song.title.entryOfTheGladiators" : {
    "translation" : "剣闘士の入場"
  },
  "song.title.helloMyBaby" : {
    "translation" : "ハローマイベイビー"
  },
  "song.title.turkeyInTheStraw" : {
    "translation" : "オクラホマミキサー"
  },
  "song.title.londonBridge" : {
    "translation" : "ロンドン橋"
  },
  "song.title.sakura" : {
    "translation" : "さくらさくら"
  },
  "song.title.mussIDenn" : {
    "translation" : "別れ"
  }
}