{
  "smartling" : {
    "translate_paths" : ["*/translation"],
    "variants_enabled" : true,
    "translate_mode" : "custom",
    "placeholder_format_custom" : ["%%[^%]+?%%", "%[^%]+?%", "##[^#]+?##", "__[^_]+?__", "[$]\\{[^\\}\\{]+?\\}", "\\{\\{[^\\}\\{]+?\\}\\}", "(?<!\\{)\\{[^\\}\\{]+?\\}(?!\\})"],
    "source_key_paths" : ["/{*}"]
  },
  "whatsNew.modal.title" : {
    "translation" : "Quoi de neuf ?"
  },
  "whatsNew.button.openInCodeLab" : {
    "translation" : "JOUE MAINTENANT DANS CODE LAB !"
  },
  "whatsNew.CodeLab_VerticalLaunch.title" : {
    "translation" : "Code Lab 2.0 !"
  },
  "whatsNew.CodeLab_VerticalLaunch.description" : {
    "translation" : "Tout nouveau, il regorge de projets comme \"Sons et Lumières\" !"
  },
  "whatsNew.CodeLab_TinyOrchestra.title" : {
    "translation" : "Petit orchestre !"
  },
  "whatsNew.CodeLab_TinyOrchestra.description" : {
    "translation" : "C'est ton propre petit orchestre et les cubes sont tes instruments !"
  },
  "whatsNew.CodeLab_MagicFortuneTeller.title" : {
    "translation" : "Voyant magique !"
  },
  "whatsNew.CodeLab_MagicFortuneTeller.description" : {
    "translation" : "Secoue Cozmo pour qu'il te dise ton avenir !"
  },
  "whatsNew.CodeLab_HotPotato.title" : {
    "translation" : "Patate chaude !"
  },
  "whatsNew.CodeLab_HotPotato.description" : {
    "translation" : "Lorsque la musique s'arrête, évite d'être bloqué avec la patate chaude !"
  },
  "whatsNew.CodeLab_FireTruckAlarm.title" : {
    "translation" : "Sirène de pompier !"
  },
  "whatsNew.CodeLab_FireTruckAlarm.description" : {
    "translation" : "Tic tac ! Une minuterie, c'est bien plus drôle avec Cozmo."
  },
  "whatsNew.CodeLab_CubeWhack.title" : {
    "translation" : "Frappe de cube !"
  },
  "whatsNew.CodeLab_CubeWhack.description" : {
    "translation" : "Frappe ce cube ! Quel est ton meilleur score ?"
  },
  "whatsNew.CodeLab_LaserSmile.title" : {
    "translation" : "Sourire laser !"
  },
  "whatsNew.CodeLab_LaserSmile.description" : {
    "translation" : "Le but est de chasser cet air renfrogné !"
  },
  "whatsNew.CodeLab_ValentinesCozmogram.title" : {
    "translation" : "Cozmogramme de la Saint-Valentin"
  },
  "whatsNew.CodeLab_ValentinesCozmogram.description" : {
    "translation" : "Offre un cadeau de Saint-Valentin façon Cozmo."
  },
  "whatsNew.CodeLab_PuttPutt.title" : {
    "translation" : "Mini-golf"
  },
  "whatsNew.CodeLab_PuttPutt.description" : {
    "translation" : "Peux-tu faire un trou en un coup ?"
  },
  "whatsNew.CodeLab_ShakeIt.title" : {
    "translation" : "Maracas !"
  },
  "whatsNew.CodeLab_ShakeIt.description" : {
    "translation" : "Fais bouger les choses avec ce nouveau jeu."
  },
  "whatsNew.CodeLab_RemoteControlRacer.title" : {
    "translation" : "Manette de Course"
  },
  "whatsNew.CodeLab_RemoteControlRacer.description" : {
    "translation" : "Vroum, vroum ! Conduis Cozmo à la vitesse maximale."
  },
  "whatsNew.CodeLab_ComplimentGenerator.title" : {
    "translation" : "Les Cozmopliments"
  },
  "whatsNew.CodeLab_ComplimentGenerator.description" : {
    "translation" : "Cozmo a quelque chose d'agréable à dire !"
  },
  "whatsNew.CodeLab_PotOGoldDetector.title" : {
    "translation" : "Chasse au trésor"
  },
  "whatsNew.CodeLab_PotOGoldDetector.description" : {
    "translation" : "La chasse au trésor ultime de la St Patrick !"
  },
  "whatsNew.CodeLab_DrivingInCircles.title" : {
    "translation" : "Tourne en rond"
  },
  "whatsNew.CodeLab_DrivingInCircles.description" : {
    "translation" : "Fais des cercles pour la journée de Pi !"
  },
  "whatsNew.CodeLab_PaddleBall.title" : {
    "translation" : "Pong"
  },
  "whatsNew.CodeLab_PaddleBall.description" : {
    "translation" : "Défie Cozmo dans un match. Utilise ta tête !"
  },
  "whatsNew.CodeLab_Constellations.title" : {
    "translation" : "Constellations"
  },
  "whatsNew.CodeLab_Constellations.description" : {
    "translation" : "Fête le jour de l'astronomie avec des constellations cosmiques."
  },
  "whatsNew.CodeLab_CozmosGarden.title" : {
    "translation" : "Le jardin de Cozmo"
  },
  "whatsNew.CodeLab_CozmosGarden.description" : {
    "translation" : "Célèbre la Journée de la Terre en faisant du jardinage avec Cozmo !"
  },
  "whatsNew.CodeLab_GuessTheNumber.title" : {
    "translation" : "Devine le nombre"
  },
  "whatsNew.CodeLab_GuessTheNumber.description" : {
    "translation" : "SOUMIS PAR JDFIGHT\u000a\u000aCozmo, le grand thaumaturge, va deviner ton nombre !"
  },
  "whatsNew.CodeLab_WakeUpCozmo.title" : {
    "translation" : "Réveille-toi Cozmo !"
  },
  "whatsNew.CodeLab_WakeUpCozmo.description" : {
    "translation" : "Qui ose perturber la sieste de Cozmo ?"
  }
}